{
    "queryCost": 1,
    "latitude": 50.180035,
    "longitude": -4.974313,
    "resolvedAddress": "50.180035,-4.974313",
    "address": "50.180035,-4.974313",
    "timezone": "Europe/London",
    "tzoffset": 1,
    "days": [
        {
            "datetime": "2023-05-19",
            "datetimeEpoch": 1684450800,
            "tempmax": 15.6,
            "tempmin": 10.2,
            "temp": 12.6,
            "feelslikemax": 15.6,
            "feelslikemin": 10.2,
            "feelslike": 12.6,
            "dew": 10,
            "humidity": 84.8,
            "precip": 0.026,
            "precipprob": 100,
            "precipcover": 4.17,
            "preciptype": [
                "rain"
            ],
            "snow": 0,
            "snowdepth": 0,
            "windgust": 38.4,
            "windspeed": 25,
            "winddir": 346.1,
            "pressure": 1028,
            "cloudcover": 64,
            "visibility": 15.9,
            "solarradiation": 142,
            "solarenergy": 11.2,
            "uvindex": 6,
            "sunrise": "05:28:29",
            "sunriseEpoch": 1684470509,
            "sunset": "21:05:12",
            "sunsetEpoch": 1684526712,
            "moonphase": 0,
            "conditions": "Rain, Partially cloudy",
            "description": "Partly cloudy throughout the day with morning rain.",
            "icon": "rain",
            "stations": [
                "F3296",
                "03827099999",
                "EGDR",
                "03808099999",
                "F8794",
                "03823099999",
                "03809099999",
                "EGHQ"
            ],
            "source": "obs"
        }
    ],
    "stations": {
        "F3296": {
            "distance": 60213,
            "latitude": 50.521,
            "longitude": -4.316,
            "useCount": 0,
            "id": "F3296",
            "name": "FW3296 Kelly Bray UK",
            "quality": 0,
            "contribution": 0
        },
        "03827099999": {
            "distance": 63895,
            "latitude": 50.35,
            "longitude": -4.117,
            "useCount": 0,
            "id": "03827099999",
            "name": "PLYMOUTH MOUNTBATTE, UK",
            "quality": 99,
            "contribution": 0
        },
        "EGDR": {
            "distance": 22606,
            "latitude": 50.08,
            "longitude": -5.25,
            "useCount": 0,
            "id": "EGDR",
            "name": "EGDR",
            "quality": 50,
            "contribution": 0
        },
        "03808099999": {
            "distance": 24735,
            "latitude": 50.217,
            "longitude": -5.317,
            "useCount": 0,
            "id": "03808099999",
            "name": "CAMBORNE, UK",
            "quality": 100,
            "contribution": 0
        },
        "F8794": {
            "distance": 64592,
            "latitude": 50.431,
            "longitude": -4.155,
            "useCount": 0,
            "id": "F8794",
            "name": "FW8794 Plymouth UK",
            "quality": 0,
            "contribution": 0
        },
        "03823099999": {
            "distance": 41790,
            "latitude": 50.5,
            "longitude": -4.667,
            "useCount": 0,
            "id": "03823099999",
            "name": "CARDINHAM BODMIN, UK",
            "quality": 99,
            "contribution": 0
        },
        "03809099999": {
            "distance": 22639,
            "latitude": 50.086,
            "longitude": -5.256,
            "useCount": 0,
            "id": "03809099999",
            "name": "CULDROSE, UK",
            "quality": 100,
            "contribution": 0
        },
        "EGHQ": {
            "distance": 27886,
            "latitude": 50.43,
            "longitude": -5,
            "useCount": 0,
            "id": "EGHQ",
            "name": "EGHQ",
            "quality": 49,
            "contribution": 0
        }
    },
    "currentConditions": {
        "datetime": "07:00:00",
        "datetimeEpoch": 1684476000,
        "temp": 11.4,
        "feelslike": 11.4,
        "humidity": 96.4,
        "dew": 10.9,
        "precip": 0,
        "precipprob": 0,
        "snow": 0,
        "snowdepth": 0,
        "preciptype": null,
        "windgust": 12.6,
        "windspeed": 8.3,
        "winddir": 333,
        "pressure": 1028.2,
        "visibility": 11.9,
        "cloudcover": 65,
        "solarradiation": 12,
        "solarenergy": 0,
        "uvindex": 0,
        "conditions": "Partially cloudy",
        "icon": "partly-cloudy-day",
        "stations": [
            "03827099999",
            "EGDR",
            "F3296",
            "03808099999",
            "03823099999",
            "EGHQ"
        ],
        "source": "obs",
        "sunrise": "05:28:29",
        "sunriseEpoch": 1684470509,
        "sunset": "21:05:12",
        "sunsetEpoch": 1684526712,
        "moonphase": 0
    }
}